risc-v/risc-v-defines.v
// Register file defines
`define NUM_REGISTERS 32
`define READ_X0_ZERO 5'b00000   // zero
`define READ_X1_RA 5'b00001     // return address
`define READ_X2_SP 5'b00010     // stack pointer 
`define READ_X3_GP 5'b00011     // global pointer
`define READ_X4_TP 5'b00100     // thread pointer
`define READ_X5_T0 5'b00101     // temporary/alternate link register
`define READ_X6_T1 5'b00110     // temporary
`define READ_X7_T2 5'b00111     // temporary
`define READ_X8_S0 5'b01000     // saved register/frame pointer
`define READ_X9_S1 5'b01001     // saved register
`define READ_X10_A0 5'b01010    // function argument/return value
`define READ_X11_A1 5'b01011    // function argument/return value
`define READ_X12_A2 5'b01100    // function argument
`define READ_X13_A3 5'b01101    // function argument
`define READ_X14_A4 5'b01110    // function argument
`define READ_X15_A5 5'b01111    // function argument
`define READ_X16_A6 5'b10000    // function argument
`define READ_X17_A7 5'b10001    // function argument
`define READ_X18_S2 5'b10010    // saved register
`define READ_X19_S3 5'b10011    // saved register
`define READ_X20_S4 5'b10100    // saved register
`define READ_X21_S5 5'b10101    // saved register
`define READ_X22_S6 5'b10110    // saved register
`define READ_X23_S7 5'b10111    // saved register
`define READ_X24_S8 5'b11000    // saved register
`define READ_X25_S9 5'b11001    // saved register
`define READ_X26_S10 5'b11010   // saved register
`define READ_X27_S11 5'b11011   // saved register
`define READ_X28_T3 5'b11100    // temporary
`define READ_X29_T4 5'b11101    // temporary
`define READ_X30_T5 5'b11110    // temporary
`define READ_X31_T6 5'b11111    // temporary

// ALU operation codes
`define ALU_ADD     4'b0000
`define ALU_SUB     4'b1000
`define ALU_SLL     4'b0001
`define ALU_SRL     4'b0101
`define ALU_SRA     4'b1101
`define ALU_SLT     4'b0010
`define ALU_SLTU    4'b0011
`define ALU_XOR     4'b0100
`define ALU_OR      4'b0110
`define ALU_AND     4'b0111
`define ALU_PASS_B  4'b1111

// Opcode values (7-bit)
`define OPCODE_R    7'b0110011  // R-type instructions (e.g., add, sub)
`define OPCODE_I    7'b0010011  // I-type instructions (e.g., addi, ori)
`define OPCODE_LOAD 7'b0000011  // Load instructions
`define OPCODE_STORE 7'b0100011 // Store instructions
`define OPCODE_BRANCH 7'b1100011 // Branch instructions
`define OPCODE_JAL  7'b1101111  // JAL (jump and link)
`define OPCODE_JALR 7'b1100111  // JALR (jump and link register)
`define OPCODE_LUI  7'b0110111  // Load Upper Immediate
`define OPCODE_AUIPC 7'b0010111 // Add Upper Immediate to PC

// Immediate types
`define IMM_I       3'b000      // I-type immediate
`define IMM_S       3'b001      // S-type immediate
`define IMM_B       3'b010      // B-type immediate (branch)
`define IMM_U       3'b011      // U-type immediate
`define IMM_J       3'b100      // J-type immediate (jump)

// Control signals
`define ALU_OP_ADD  3'b000
`define ALU_OP_SUB  3'b001
`define ALU_OP_LUI  3'b010
`define ALU_OP_SRL  3'b011
`define ALU_OP_SRA  3'b100
`define ALU_OP_AND  3'b101
`define ALU_OP_OR   3'b110
`define ALU_OP_XOR  3'b111

// CSR register addresses (12-bit)
`define CSR_MSTATUS   12'h300   // Machine status register
`define CSR_MISA      12'h301   // ISA and extensions
`define CSR_MEPC      12'h341   // Machine exception program counter
`define CSR_MCAUSE    12'h342   // Machine cause register
`define CSR_MTVAL     12'h343   // Machine trap value
`define CSR_MTVEC     12'h305   // Machine trap-vector base address
`define CSR_MSCRATCH  12'h340   // Machine scratch register

risc-v/control_unit/control_unit.v
`include "../risc-v-defines.v"

module control_unit (
    input wire [6:0] opcode,   // Opcode from the instruction
    input wire [2:0] funct3,   // funct3 field from the instruction
    input wire [6:0] funct7,   // funct7 field from the instruction
    input wire zero,           // Zero flag for branches
    output reg reg_write,      // Register write enable
    output reg alu_src,        // ALU source select
    output reg mem_write,      // Memory write enable
    output reg mem_read,       // Memory read enable
    output reg mem_to_reg,     // Memory to register select
    output reg branch,         // Branch enable
    output reg jump,           // Jump enable
    output reg [2:0] alu_op    // ALU operation
);

    always @(*) begin
        // Default values for all outputs
        reg_write = 0;
        alu_src = 0;
        mem_write = 0;
        mem_read = 0;
        mem_to_reg = 0;
        branch = 0;
        jump = 0;
        alu_op = 3'b000; // Default ALU operation (add)

        case (opcode)
            `OPCODE_R: begin // R-Type
                reg_write = 1;
                alu_src = 0;
                alu_op = funct3; // ALU operation depends on funct3/funct7
            end
            `OPCODE_I: begin // I-Type (ALU)
                reg_write = 1;
                alu_src = 1;
                alu_op = funct3;
            end
            `OPCODE_LOAD: begin // Load
                reg_write = 1;
                mem_read = 1;
                mem_to_reg = 1;
                alu_src = 1;
            end
            `OPCODE_STORE: begin // Store
                mem_write = 1;
                alu_src = 1;
            end
            `OPCODE_BRANCH: begin // Branch
                branch = 1;
                alu_op = 3'b001; // Subtract for branch comparison
            end
            `OPCODE_JAL: begin // JAL
                jump = 1;
                reg_write = 1;
            end
            `OPCODE_JALR: begin // JALR
                jump = 1;
                reg_write = 1;
                alu_src = 1;
            end
            `OPCODE_LUI: begin // LUI
                reg_write = 1;
                alu_src = 1;
                alu_op = 3'b010; // Custom ALU op for LUI
            end
            `OPCODE_AUIPC: begin // AUIPC
                reg_write = 1;
                alu_src = 1;
                alu_op = 3'b011; // Custom ALU op for AUIPC
            end
        endcase
    end
endmodule

risc-v/control_unit/control_unit_tb.v
`timescale 1ns/1ps
`include "../risc-v-defines.v"

module control_unit_tb;

    // Testbench signals
    reg [6:0] opcode;
    reg [2:0] funct3;
    reg [6:0] funct7;
    reg zero;
    wire reg_write;
    wire alu_src;
    wire mem_write;
    wire mem_read;
    wire mem_to_reg;
    wire branch;
    wire jump;
    wire [2:0] alu_op;

    // Instantiate the control unit
    control_unit uut (
        .opcode(opcode),
        .funct3(funct3),
        .funct7(funct7),
        .zero(zero),
        .reg_write(reg_write),
        .alu_src(alu_src),
        .mem_write(mem_write),
        .mem_read(mem_read),
        .mem_to_reg(mem_to_reg),
        .branch(branch),
        .jump(jump),
        .alu_op(alu_op)
    );

    // Test procedure
    initial begin
        $dumpfile("control_unit_tb.vcd");
        $dumpvars(0, control_unit_tb);

        // Test R-type instruction
        opcode = `OPCODE_R; funct3 = 3'b000; funct7 = 7'b0000000; zero = 0;
        #10; // Wait 10 ns
        $display("R-Type | reg_write=%b alu_src=%b mem_write=%b mem_read=%b mem_to_reg=%b branch=%b jump=%b alu_op=%b",
                 reg_write, alu_src, mem_write, mem_read, mem_to_reg, branch, jump, alu_op);

        // Test I-type instruction
        opcode = `OPCODE_I; funct3 = 3'b010; funct7 = 7'b0000000; zero = 0;
        #10;
        $display("I-Type | reg_write=%b alu_src=%b mem_write=%b mem_read=%b mem_to_reg=%b branch=%b jump=%b alu_op=%b",
                 reg_write, alu_src, mem_write, mem_read, mem_to_reg, branch, jump, alu_op);

        // Test Load instruction
        opcode = `OPCODE_LOAD; funct3 = 3'b000; funct7 = 7'b0000000; zero = 0;
        #10;
        $display("Load   | reg_write=%b alu_src=%b mem_write=%b mem_read=%b mem_to_reg=%b branch=%b jump=%b alu_op=%b",
                 reg_write, alu_src, mem_write, mem_read, mem_to_reg, branch, jump, alu_op);

        // Test Store instruction
        opcode = `OPCODE_STORE; funct3 = 3'b010; funct7 = 7'b0000000; zero = 0;
        #10;
        $display("Store  | reg_write=%b alu_src=%b mem_write=%b mem_read=%b mem_to_reg=%b branch=%b jump=%b alu_op=%b",
                 reg_write, alu_src, mem_write, mem_read, mem_to_reg, branch, jump, alu_op);

        // Test Branch instruction
        opcode = `OPCODE_BRANCH; funct3 = 3'b000; funct7 = 7'b0000000; zero = 1;
        #10;
        $display("Branch | reg_write=%b alu_src=%b mem_write=%b mem_read=%b mem_to_reg=%b branch=%b jump=%b alu_op=%b",
                 reg_write, alu_src, mem_write, mem_read, mem_to_reg, branch, jump, alu_op);

        // Test JAL instruction
        opcode = `OPCODE_JAL; funct3 = 3'b000; funct7 = 7'b0000000; zero = 0;
        #10;
        $display("JAL    | reg_write=%b alu_src=%b mem_write=%b mem_read=%b mem_to_reg=%b branch=%b jump=%b alu_op=%b",
                 reg_write, alu_src, mem_write, mem_read, mem_to_reg, branch, jump, alu_op);

        // Test JALR instruction
        opcode = `OPCODE_JALR; funct3 = 3'b000; funct7 = 7'b0000000; zero = 0;
        #10;
        $display("JALR   | reg_write=%b alu_src=%b mem_write=%b mem_read=%b mem_to_reg=%b branch=%b jump=%b alu_op=%b",
                 reg_write, alu_src, mem_write, mem_read, mem_to_reg, branch, jump, alu_op);

        // Test LUI instruction
        opcode = `OPCODE_LUI; funct3 = 3'b000; funct7 = 7'b0000000; zero = 0;
        #10;
        $display("LUI    | reg_write=%b alu_src=%b mem_write=%b mem_read=%b mem_to_reg=%b branch=%b jump=%b alu_op=%b",
                 reg_write, alu_src, mem_write, mem_read, mem_to_reg, branch, jump, alu_op);

        // Test AUIPC instruction
        opcode = `OPCODE_AUIPC; funct3 = 3'b000; funct7 = 7'b0000000; zero = 0;
        #10;
        $display("AUIPC  | reg_write=%b alu_src=%b mem_write=%b mem_read=%b mem_to_reg=%b branch=%b jump=%b alu_op=%b",
                 reg_write, alu_src, mem_write, mem_read, mem_to_reg, branch, jump, alu_op);

        $finish; // End simulation
    end
endmodule

risc-v/control_unit/control_unit_tb.vcd
$date
	Sat Nov 16 10:58:21 2024
$end
$version
	Icarus Verilog
$end
$timescale
	1ps
$end
$scope module control_unit_tb $end
$var wire 1 ! reg_write $end
$var wire 1 " mem_write $end
$var wire 1 # mem_to_reg $end
$var wire 1 $ mem_read $end
$var wire 1 % jump $end
$var wire 1 & branch $end
$var wire 1 ' alu_src $end
$var wire 3 ( alu_op [2:0] $end
$var reg 3 ) funct3 [2:0] $end
$var reg 7 * funct7 [6:0] $end
$var reg 7 + opcode [6:0] $end
$var reg 1 , zero $end
$scope module uut $end
$var wire 3 - funct3 [2:0] $end
$var wire 7 . funct7 [6:0] $end
$var wire 7 / opcode [6:0] $end
$var wire 1 , zero $end
$var reg 3 0 alu_op [2:0] $end
$var reg 1 ' alu_src $end
$var reg 1 & branch $end
$var reg 1 % jump $end
$var reg 1 $ mem_read $end
$var reg 1 # mem_to_reg $end
$var reg 1 " mem_write $end
$var reg 1 ! reg_write $end
$upscope $end
$upscope $end
$enddefinitions $end
$comment Show the parameter values. $end
$dumpall
$end
#0
$dumpvars
b0 0
b110011 /
b0 .
b0 -
0,
b110011 +
b0 *
b0 )
b0 (
0'
0&
0%
0$
0#
0"
1!
$end
#10000
b10 (
b10 0
1'
1!
b10 )
b10 -
b10011 +
b10011 /
#20000
1#
1$
b0 (
b0 0
1'
1!
b0 )
b0 -
b11 +
b11 /
#30000
1"
0#
0$
1'
0!
b10 )
b10 -
b100011 +
b100011 /
#40000
b1 (
b1 0
1&
0"
0'
1,
b0 )
b0 -
b1100011 +
b1100011 /
#50000
1!
1%
b0 (
b0 0
0&
0,
b1101111 +
b1101111 /
#60000
1'
1%
1!
b1100111 +
b1100111 /
#70000
b10 (
b10 0
0%
1'
1!
b110111 +
b110111 /
#80000
b11 (
b11 0
1'
1!
b10111 +
b10111 /
