risc-v/risc-v-defines.v
// Register file defines
`define NUM_REGISTERS 32
`define READ_X0_ZERO 5'b00000   // zero
`define READ_X1_RA 5'b00001     // return address
`define READ_X2_SP 5'b00010     // stack pointer 
`define READ_X3_GP 5'b00011     // global pointer
`define READ_X4_TP 5'b00100     // thread pointer
`define READ_X5_T0 5'b00101     // temporary/alternate link register
`define READ_X6_T1 5'b00110     // temporary
`define READ_X7_T2 5'b00111     // temporary
`define READ_X8_S0 5'b01000     // saved register/frame pointer
`define READ_X9_S1 5'b01001     // saved register
`define READ_X10_A0 5'b01010    // function argument/return value
`define READ_X11_A1 5'b01011    // function argument/return value
`define READ_X12_A2 5'b01100    // function argument
`define READ_X13_A3 5'b01101    // function argument
`define READ_X14_A4 5'b01110    // function argument
`define READ_X15_A5 5'b01111    // function argument
`define READ_X16_A6 5'b10000    // function argument
`define READ_X17_A7 5'b10001    // function argument
`define READ_X18_S2 5'b10010    // saved register
`define READ_X19_S3 5'b10011    // saved register
`define READ_X20_S4 5'b10100    // saved register
`define READ_X21_S5 5'b10101    // saved register
`define READ_X22_S6 5'b10110    // saved register
`define READ_X23_S7 5'b10111    // saved register
`define READ_X24_S8 5'b11000    // saved register
`define READ_X25_S9 5'b11001    // saved register
`define READ_X26_S10 5'b11010   // saved register
`define READ_X27_S11 5'b11011   // saved register
`define READ_X28_T3 5'b11100    // temporary
`define READ_X29_T4 5'b11101    // temporary
`define READ_X30_T5 5'b11110    // temporary
`define READ_X31_T6 5'b11111    // temporary

// ALU operation codes
`define ALU_ADD     4'b0000
`define ALU_SUB     4'b1000
`define ALU_SLL     4'b0001
`define ALU_SRL     4'b0101
`define ALU_SRA     4'b1101
`define ALU_SLT     4'b0010
`define ALU_SLTU    4'b0011
`define ALU_XOR     4'b0100
`define ALU_OR      4'b0110
`define ALU_AND     4'b0111
`define ALU_PASS_B  4'b1111

// Opcode values (7-bit)
`define OPCODE_R    7'b0110011  // R-type instructions (e.g., add, sub)
`define OPCODE_I    7'b0010011  // I-type instructions (e.g., addi, ori)
`define OPCODE_LOAD 7'b0000011  // Load instructions
`define OPCODE_STORE 7'b0100011 // Store instructions
`define OPCODE_BRANCH 7'b1100011 // Branch instructions
`define OPCODE_JAL  7'b1101111  // JAL (jump and link)
`define OPCODE_JALR 7'b1100111  // JALR (jump and link register)
`define OPCODE_LUI  7'b0110111  // Load Upper Immediate
`define OPCODE_AUIPC 7'b0010111 // Add Upper Immediate to PC

// Immediate types
`define IMM_I       3'b000      // I-type immediate
`define IMM_S       3'b001      // S-type immediate
`define IMM_B       3'b010      // B-type immediate (branch)
`define IMM_U       3'b011      // U-type immediate
`define IMM_J       3'b100      // J-type immediate (jump)

// Control signals
`define ALU_OP_ADD  3'b000
`define ALU_OP_SUB  3'b001
`define ALU_OP_LUI  3'b010
`define ALU_OP_SRL  3'b011
`define ALU_OP_SRA  3'b100
`define ALU_OP_AND  3'b101
`define ALU_OP_OR   3'b110
`define ALU_OP_XOR  3'b111

// CSR register addresses (12-bit)
`define CSR_MSTATUS   12'h300   // Machine status register
`define CSR_MISA      12'h301   // ISA and extensions
`define CSR_MEPC      12'h341   // Machine exception program counter
`define CSR_MCAUSE    12'h342   // Machine cause register
`define CSR_MTVAL     12'h343   // Machine trap value
`define CSR_MTVEC     12'h305   // Machine trap-vector base address
`define CSR_MSCRATCH  12'h340   // Machine scratch register

risc-v/instr_mem/imem.v
`include "../risc-v-defines.v"

module imem (
    input wire [31:0] addr,       // Address input (usually the PC value)
    output reg [31:0] instruction // Output instruction at the given address
);

    parameter ROM_WIDTH = 32;
    parameter ROM_ADDR_BITS = 8;
    (* ROM_STYLE="{AUTO |DISTRIBUTED |BLOCK}" *)
    reg [ROM_WIDTH-1:0] ROM [(2**ROM_ADDR_BITS)-1:0];

    initial begin
        ROM[0] = 32'h40000593;
        ROM[1] = 32'h40058593;
        ROM[2] = 32'h0145a803;
        ROM[3] = 32'hfe080ee3;
        ROM[4] = 32'h0005a603;
        ROM[5] = 32'h0045a683;
        ROM[6] = 32'h00c5a703;
        ROM[7] = 32'h0105a783;
        ROM[8] = 32'hfd060613;
        ROM[9] = 32'hfd068693;
        ROM[10] = 32'hfd070713;
        ROM[11] = 32'hfd078793;
        ROM[12] = 32'h00060293;
        ROM[13] = 32'h00070313;
        ROM[14] = 32'h00900393;
        ROM[15] = 32'h00038a63;
        ROM[16] = 32'h00560633;
        ROM[17] = 32'h00670733;
        ROM[18] = 32'hfff38393;
        ROM[19] = 32'hff1ff0ef;
        ROM[20] = 32'h00d60633;
        ROM[21] = 32'h00f70733;
        ROM[22] = 32'h00c002b3;
        ROM[23] = 32'hfff70713;
        ROM[24] = 32'h00070863;
        ROM[25] = 32'h00560633;
        ROM[26] = 32'hfff70713;
        ROM[27] = 32'hff5ff0ef;
        ROM[28] = 32'h00a00393;
        ROM[29] = 32'h00060ab3;
        ROM[30] = 32'h00000b13;
        ROM[31] = 32'h007ac863;
        ROM[32] = 32'h407a8ab3;
        ROM[33] = 32'h001b0b13;
        ROM[34] = 32'hff5ff0ef;
        ROM[35] = 32'h00000b93;
        ROM[36] = 32'h007b4863;
        ROM[37] = 32'h407b0b33;
        ROM[38] = 32'h001b8b93;
        ROM[39] = 32'hff5ff0ef;
        ROM[40] = 32'h00000c13;
        ROM[41] = 32'h007bc863;
        ROM[42] = 32'h407b8bb3;
        ROM[43] = 32'h001c0c13;
        ROM[44] = 32'hff5ff0ef;

        ROM[45] = 32'h0385a223;
        ROM[46] = 32'h0375a023;
        ROM[47] = 32'h0165ae23;
        ROM[48] = 32'h0155ac23;

        ROM[49] = 32'hf45ff0ef;

    end

    always @(*) begin
        // Divide addr by 4 to get the instruction index (since addr is byte-addressed)
        instruction = ROM[addr[11:2]];  // Using bits [11:2] for word-aligned access
    end

endmodule

risc-v/instr_mem/imem_tb.v
`timescale 1ns/1ps
`include "../risc-v-defines.v"


module imem_tb;

    reg [31:0] addr;             // Address input
    wire [31:0] instruction;     // Output instruction

    // Instantiate the IMEM module
    imem uut (
        .addr(addr),
        .instruction(instruction)
    );

    parameter CLK_PERIOD = 10;

    initial begin
        $dumpfile("imem_tb.vcd");
        $dumpvars(0, imem_tb);

        $display("Starting IMEM test...");

        // Test predefined ROM values
        addr = 32'h00000000; #CLK_PERIOD;
        $display("Addr: %h, Instruction: %h (Expected: 40000593)", addr, instruction);

        addr = 32'h00000004; #CLK_PERIOD;
        $display("Addr: %h, Instruction: %h (Expected: 40058593)", addr, instruction);

        addr = 32'h00000008; #CLK_PERIOD;
        $display("Addr: %h, Instruction: %h (Expected: 0145a803)", addr, instruction);

        addr = 32'h0000000C; #CLK_PERIOD;
        $display("Addr: %h, Instruction: %h (Expected: fe080ee3)", addr, instruction);

        addr = 32'h00000010; #CLK_PERIOD;
        $display("Addr: %h, Instruction: %h (Expected: 0005a603)", addr, instruction);

        addr = 32'h00000014; #CLK_PERIOD;
        $display("Addr: %h, Instruction: %h (Expected: 0045a683)", addr, instruction);

        addr = 32'h000000B4; #CLK_PERIOD;
        $display("Addr: %h, Instruction: %h (Expected: 407b8bb3)", addr, instruction);

        addr = 32'h000000C4; #CLK_PERIOD;
        $display("Addr: %h, Instruction: %h (Expected: f45ff0ef)", addr, instruction);

        // Access uninitialized ROM address
        addr = 32'h000000C8; #CLK_PERIOD;
        $display("Addr: %h, Instruction: %h (Expected: 00000000)", addr, instruction);

        $display("IMEM test completed.");
        $finish;
    end

endmodule

risc-v/instr_mem/imem_tb.vcd
$date
	Sat Nov 16 10:43:41 2024
$end
$version
	Icarus Verilog
$end
$timescale
	1ps
$end
$scope module imem_tb $end
$var wire 32 ! instruction [31:0] $end
$var parameter 32 " CLK_PERIOD $end
$var reg 32 # addr [31:0] $end
$scope module uut $end
$var wire 32 $ addr [31:0] $end
$var parameter 32 % ROM_ADDR_BITS $end
$var parameter 32 & ROM_WIDTH $end
$var reg 32 ' instruction [31:0] $end
$upscope $end
$upscope $end
$enddefinitions $end
$comment Show the parameter values. $end
$dumpall
b100000 &
b1000 %
b1010 "
$end
#0
$dumpvars
b1000000000000000000010110010011 '
b0 $
b0 #
b1000000000000000000010110010011 !
$end
#10000
b1000000000001011000010110010011 !
b1000000000001011000010110010011 '
b100 #
b100 $
#20000
b1010001011010100000000011 !
b1010001011010100000000011 '
b1000 #
b1000 $
#30000
b11111110000010000000111011100011 !
b11111110000010000000111011100011 '
b1100 #
b1100 $
#40000
b1011010011000000011 !
b1011010011000000011 '
b10000 #
b10000 $
#50000
b10001011010011010000011 !
b10001011010011010000011 '
b10100 #
b10100 $
#60000
b11100001011010001000100011 !
b11100001011010001000100011 '
b10110100 #
b10110100 $
#70000
b11110100010111111111000011101111 !
b11110100010111111111000011101111 '
b11000100 #
b11000100 $
#80000
bx !
bx '
b11001000 #
b11001000 $
