risc-v/csr/csr.v
module csr (
    input wire clk,                // Clock signal
    input wire rst,                // Reset signal (active high)
    input wire csr_write,          // Write enable signal
    input wire csr_read,           // Read enable signal
    input wire [11:0] csr_addr,    // CSR address (12-bit)
    input wire [31:0] csr_write_data, // Data to write to the CSR
    output reg [31:0] csr_read_data   // Data read from the CSR
);

    // Define CSR addresses
    localparam MSTATUS   = 12'h300;  // Machine Status Register
    localparam MTVEC     = 12'h305;  // Machine Trap-Vector Base Address
    localparam MEPC      = 12'h341;  // Machine Exception Program Counter
    localparam MCAUSE    = 12'h342;  // Machine Cause Register

    // CSR register file
    reg [31:0] csr_file [0:4095]; // 4096 CSRs (12-bit address space)

    // Reset initialization
    integer i;
    always @(posedge clk or posedge rst) begin
        if (rst) begin
            for (i = 0; i < 4096; i = i + 1) begin
                csr_file[i] <= 32'h0; // Clear all CSRs
            end
            // Initialize specific CSRs
            csr_file[MSTATUS] <= 32'h0;
            csr_file[MTVEC]   <= 32'h0;
            csr_file[MEPC]    <= 32'h0;
            csr_file[MCAUSE]  <= 32'h0;
        end else if (csr_write) begin
            csr_file[csr_addr] <= csr_write_data; // Write to CSR
        end
    end

    // CSR read operation
    always @(*) begin
        if (csr_read) begin
            csr_read_data = csr_file[csr_addr];
        end else begin
            csr_read_data = 32'h0;
        end
    end

endmodule

risc-v/csr/csr_tb.v
`timescale 1ns / 1ps

module csr_tb;

    // Testbench signals
    reg clk;                     // Clock signal
    reg rst;                     // Reset signal
    reg csr_write;               // Write enable
    reg csr_read;                // Read enable
    reg [11:0] csr_addr;         // CSR address
    reg [31:0] csr_write_data;   // Data to write
    wire [31:0] csr_read_data;   // Data read from CSR

    // DUT instantiation
    csr uut (
        .clk(clk),
        .rst(rst),
        .csr_write(csr_write),
        .csr_read(csr_read),
        .csr_addr(csr_addr),
        .csr_write_data(csr_write_data),
        .csr_read_data(csr_read_data)
    );

    // Clock generation
    initial begin
        clk = 0;
        forever #5 clk = ~clk; // 10ns clock period
    end

    // Test procedure
    initial begin
        $dumpfile("csr_tb.vcd");
        $dumpvars(0, csr_tb);

        // Initialize inputs
        rst = 0;
        csr_write = 0;
        csr_read = 0;
        csr_addr = 12'h000;
        csr_write_data = 32'h00000000;

        // Apply reset
        $display("Applying reset...");
        rst = 1;
        #10;
        rst = 0;
        #10;

        // Verify reset state
        csr_read = 1;
        csr_addr = 12'h300; // MSTATUS
        #10;
        $display("Read MSTATUS after reset: 0x%h", csr_read_data);

        // Write to MSTATUS
        $display("Writing to MSTATUS...");
        csr_read = 0;
        csr_write = 1;
        csr_addr = 12'h300; // MSTATUS
        csr_write_data = 32'hdeadbeef;
        #10;
        csr_write = 0;

        // Read back MSTATUS
        csr_read = 1;
        #10;
        $display("Read MSTATUS after write: 0x%h", csr_read_data);

        // Write to another CSR (MEPC)
        $display("Writing to MEPC...");
        csr_read = 0;
        csr_write = 1;
        csr_addr = 12'h341; // MEPC
        csr_write_data = 32'h12345678;
        #10;
        csr_write = 0;

        // Read back MEPC
        csr_read = 1;
        csr_addr = 12'h341; // MEPC
        #10;
        $display("Read MEPC after write: 0x%h", csr_read_data);

        // Invalid address read
        $display("Reading from an invalid address...");
        csr_read = 1;
        csr_addr = 12'hFFF; // Invalid address
        #10;
        $display("Read invalid CSR: 0x%h", csr_read_data);

        $finish;
    end

endmodule

risc-v/csr/csr_tb.vcd
$date
	Sun Nov 17 17:37:49 2024
$end
$version
	Icarus Verilog
$end
$timescale
	1ps
$end
$scope module csr_tb $end
$var wire 32 ! csr_read_data [31:0] $end
$var reg 1 " clk $end
$var reg 12 # csr_addr [11:0] $end
$var reg 1 $ csr_read $end
$var reg 1 % csr_write $end
$var reg 32 & csr_write_data [31:0] $end
$var reg 1 ' rst $end
$scope module uut $end
$var wire 1 " clk $end
$var wire 12 ( csr_addr [11:0] $end
$var wire 1 $ csr_read $end
$var wire 1 % csr_write $end
$var wire 32 ) csr_write_data [31:0] $end
$var wire 1 ' rst $end
$var parameter 12 * MCAUSE $end
$var parameter 12 + MEPC $end
$var parameter 12 , MSTATUS $end
$var parameter 12 - MTVEC $end
$var reg 32 . csr_read_data [31:0] $end
$var integer 32 / i [31:0] $end
$upscope $end
$upscope $end
$enddefinitions $end
$comment Show the parameter values. $end
$dumpall
b1100000101 -
b1100000000 ,
b1101000001 +
b1101000010 *
$end
#0
$dumpvars
b1000000000000 /
b0 .
b0 )
b0 (
1'
b0 &
0%
0$
b0 #
0"
b0 !
$end
#5000
b1000000000000 /
1"
#10000
0"
0'
#15000
1"
#20000
0"
b1100000000 #
b1100000000 (
1$
#25000
1"
#30000
0"
b11011110101011011011111011101111 &
b11011110101011011011111011101111 )
1%
0$
#35000
1"
#40000
b11011110101011011011111011101111 !
b11011110101011011011111011101111 .
0"
1$
0%
#45000
1"
#50000
b0 !
b0 .
0"
b10010001101000101011001111000 &
b10010001101000101011001111000 )
b1101000001 #
b1101000001 (
1%
0$
#55000
1"
#60000
b10010001101000101011001111000 !
b10010001101000101011001111000 .
0"
1$
0%
#65000
1"
#70000
b0 !
b0 .
0"
b111111111111 #
b111111111111 (
