risc-v/risc-v-defines.v
// Register file defines
`define NUM_REGISTERS 32
`define READ_X0_ZERO 5'b00000   // zero
`define READ_X1_RA 5'b00001     // return address
`define READ_X2_SP 5'b00010     // stack pointer 
`define READ_X3_GP 5'b00011     // global pointer
`define READ_X4_TP 5'b00100     // thread pointer
`define READ_X5_T0 5'b00101     // temporary/alternate link register
`define READ_X6_T1 5'b00110     // temporary
`define READ_X7_T2 5'b00111     // temporary
`define READ_X8_S0 5'b01000     // saved register/frame pointer
`define READ_X9_S1 5'b01001     // saved register
`define READ_X10_A0 5'b01010    // function argument/return value
`define READ_X11_A1 5'b01011    // function argument/return value
`define READ_X12_A2 5'b01100    // function argument
`define READ_X13_A3 5'b01101    // function argument
`define READ_X14_A4 5'b01110    // function argument
`define READ_X15_A5 5'b01111    // function argument
`define READ_X16_A6 5'b10000    // function argument
`define READ_X17_A7 5'b10001    // function argument
`define READ_X18_S2 5'b10010    // saved register
`define READ_X19_S3 5'b10011    // saved register
`define READ_X20_S4 5'b10100    // saved register
`define READ_X21_S5 5'b10101    // saved register
`define READ_X22_S6 5'b10110    // saved register
`define READ_X23_S7 5'b10111    // saved register
`define READ_X24_S8 5'b11000    // saved register
`define READ_X25_S9 5'b11001    // saved register
`define READ_X26_S10 5'b11010   // saved register
`define READ_X27_S11 5'b11011   // saved register
`define READ_X28_T3 5'b11100    // temporary
`define READ_X29_T4 5'b11101    // temporary
`define READ_X30_T5 5'b11110    // temporary
`define READ_X31_T6 5'b11111    // temporary

// ALU operation codes
`define ALU_ADD     4'b0000
`define ALU_SUB     4'b1000
`define ALU_SLL     4'b0001
`define ALU_SRL     4'b0101
`define ALU_SRA     4'b1101
`define ALU_SLT     4'b0010
`define ALU_SLTU    4'b0011
`define ALU_XOR     4'b0100
`define ALU_OR      4'b0110
`define ALU_AND     4'b0111
`define ALU_PASS_B  4'b1111

// Opcode values (7-bit)
`define OPCODE_R    7'b0110011  // R-type instructions (e.g., add, sub)
`define OPCODE_I    7'b0010011  // I-type instructions (e.g., addi, ori)
`define OPCODE_LOAD 7'b0000011  // Load instructions
`define OPCODE_STORE 7'b0100011 // Store instructions
`define OPCODE_BRANCH 7'b1100011 // Branch instructions
`define OPCODE_JAL  7'b1101111  // JAL (jump and link)
`define OPCODE_JALR 7'b1100111  // JALR (jump and link register)
`define OPCODE_LUI  7'b0110111  // Load Upper Immediate
`define OPCODE_AUIPC 7'b0010111 // Add Upper Immediate to PC

// Immediate types
`define IMM_I       3'b000      // I-type immediate
`define IMM_S       3'b001      // S-type immediate
`define IMM_B       3'b010      // B-type immediate (branch)
`define IMM_U       3'b011      // U-type immediate
`define IMM_J       3'b100      // J-type immediate (jump)

// Control signals
`define ALU_OP_ADD  3'b000
`define ALU_OP_SUB  3'b001
`define ALU_OP_LUI  3'b010
`define ALU_OP_SRL  3'b011
`define ALU_OP_SRA  3'b100
`define ALU_OP_AND  3'b101
`define ALU_OP_OR   3'b110
`define ALU_OP_XOR  3'b111

// CSR register addresses (12-bit)
`define CSR_MSTATUS   12'h300   // Machine status register
`define CSR_MISA      12'h301   // ISA and extensions
`define CSR_MEPC      12'h341   // Machine exception program counter
`define CSR_MCAUSE    12'h342   // Machine cause register
`define CSR_MTVAL     12'h343   // Machine trap value
`define CSR_MTVEC     12'h305   // Machine trap-vector base address
`define CSR_MSCRATCH  12'h340   // Machine scratch register

risc-v/program_counter/pc.v
`include "../risc-v-defines.v"

module pc (
    input wire clk,             // Clock input
    input wire rst,             // Reset input (active high)
    input wire en,              // Enable signal (if not enabled, PC holds its value)
    input wire [31:0] next_pc,  // Next PC value to be loaded into the PC
    output reg [31:0] pc_out    // Current PC value
);

    parameter RESET_PC_VALUE = 32'h00000000;

    always @(posedge clk or posedge rst) begin
        if (rst) begin
            // Reset the PC to 0 on reset
            pc_out <= RESET_PC_VALUE;
        end else if (en) begin
            // Update the PC if enabled
            pc_out <= next_pc;
        end else begin
            // Default behavior: increment PC by 4 for the next instruction
            pc_out <= pc_out + 4;
        end
    end

endmodule

risc-v/program_counter/pc_tb.v
module pc_tb;
    reg clk;
    reg rst;
    reg en;
    reg [31:0] next_pc;
    wire [31:0] pc_out;

    // Instantiate the Program Counter
    pc pc_uut (
        .clk(clk),
        .rst(rst),
        .en(en),
        .next_pc(next_pc),
        .pc_out(pc_out)
    );

    // Clock generation
    always #5 clk = ~clk; // Clock period of 10 units

    initial begin
        $dumpfile("pc_tb.vcd");
        $dumpvars(0, pc_tb);
        // Initialize signals
        clk = 0;
        rst = 0;
        en = 0;
        next_pc = 0;

        // Test 1: Apply reset
        $display("Test 1: Applying reset");
        rst = 1;
        #10;
        rst = 0;
        $display("PC after reset: %h (expected: 0)", pc_out);
        #10;

        // Test 2: Increment PC when en is low
        $display("Test 2: Increment PC by 4 when en is low");
        en = 0;
        #10;
        $display("PC value: %h (expected: 4)", pc_out);
        #10;
        $display("PC value: %h (expected: 8)", pc_out);
        #10;

        // Test 3: Load specific next_pc value when en is high
        $display("Test 3: Loading a specific next_pc value");
        en = 1;
        next_pc = 32'h00000020;
        #10;
        $display("PC value after loading next_pc: %h (expected: 20)", pc_out);
        en = 0;  // Disable PC update
        #10;
        $display("PC value: %h (expected: 24)", pc_out);

        // Test 4: Increment again after loading
        #10;
        $display("PC value: %h (expected: 28)", pc_out);

        // Finish simulation
        $finish;
    end

endmodule

risc-v/program_counter/pc_tb.vcd
$date
	Sat Nov 16 10:38:37 2024
$end
$version
	Icarus Verilog
$end
$timescale
	1ps
$end
$scope module pc_tb $end
$var wire 32 ! pc_out [31:0] $end
$var reg 1 " clk $end
$var reg 1 # en $end
$var reg 32 $ next_pc [31:0] $end
$var reg 1 % rst $end
$scope module pc_uut $end
$var wire 1 " clk $end
$var wire 1 # en $end
$var wire 32 & next_pc [31:0] $end
$var wire 1 % rst $end
$var parameter 32 ' RESET_PC_VALUE $end
$var reg 32 ( pc_out [31:0] $end
$upscope $end
$upscope $end
$enddefinitions $end
$comment Show the parameter values. $end
$dumpall
b0 '
$end
#0
$dumpvars
b0 (
b0 &
1%
b0 $
0#
0"
b0 !
$end
#5
1"
#10
0"
0%
#15
b100 !
b100 (
1"
#20
0"
#25
b1000 !
b1000 (
1"
#30
0"
#35
b1100 !
b1100 (
1"
#40
0"
#45
b10000 !
b10000 (
1"
#50
0"
b100000 $
b100000 &
1#
#55
b100000 !
b100000 (
1"
#60
0"
0#
#65
b100100 !
b100100 (
1"
#70
0"
#75
b101000 !
b101000 (
1"
