risc-v/risc-v-defines.v
// Register file defines
`define NUM_REGISTERS 32
`define READ_X0_ZERO 5'b00000   // zero
`define READ_X1_RA 5'b00001     // return address
`define READ_X2_SP 5'b00010     // stack pointer 
`define READ_X3_GP 5'b00011     // global pointer
`define READ_X4_TP 5'b00100     // thread pointer
`define READ_X5_T0 5'b00101     // temporary/alternate link register
`define READ_X6_T1 5'b00110     // temporary
`define READ_X7_T2 5'b00111     // temporary
`define READ_X8_S0 5'b01000     // saved register/frame pointer
`define READ_X9_S1 5'b01001     // saved register
`define READ_X10_A0 5'b01010    // function argument/return value
`define READ_X11_A1 5'b01011    // function argument/return value
`define READ_X12_A2 5'b01100    // function argument
`define READ_X13_A3 5'b01101    // function argument
`define READ_X14_A4 5'b01110    // function argument
`define READ_X15_A5 5'b01111    // function argument
`define READ_X16_A6 5'b10000    // function argument
`define READ_X17_A7 5'b10001    // function argument
`define READ_X18_S2 5'b10010    // saved register
`define READ_X19_S3 5'b10011    // saved register
`define READ_X20_S4 5'b10100    // saved register
`define READ_X21_S5 5'b10101    // saved register
`define READ_X22_S6 5'b10110    // saved register
`define READ_X23_S7 5'b10111    // saved register
`define READ_X24_S8 5'b11000    // saved register
`define READ_X25_S9 5'b11001    // saved register
`define READ_X26_S10 5'b11010   // saved register
`define READ_X27_S11 5'b11011   // saved register
`define READ_X28_T3 5'b11100    // temporary
`define READ_X29_T4 5'b11101    // temporary
`define READ_X31_T6 5'b11110    // temporary
`define READ_X30_T5 5'b11111    // temporary

risc-v/program_counter/pc.v
`include "../risc-v-defines.v"

module pc (
    input wire clk,        // Clock input
    input wire rst,        // Reset input (active high)
    input wire en,         // Enable signal (if not enabled, PC holds its value)
    input wire [31:0] next_pc, // Next PC value to be loaded into the PC
    output reg [31:0] pc_out  // Current PC value
);

    always @(posedge clk or posedge rst) begin
        if (rst) begin
            // Reset the PC to 0 on reset
            pc_out <= 32'h00000000;
        end else if (en) begin
            // Update the PC if enabled
            pc_out <= next_pc;
        end
    end

endmodule

risc-v/program_counter/pc_tb.v
module pc_tb;
    reg clk;
    reg rst;
    reg en;
    reg [31:0] next_pc;
    wire [31:0] pc_out;

    // Instantiate the Program Counter
    pc pc_uut (
        .clk(clk),
        .rst(rst),
        .en(en),
        .next_pc(next_pc),
        .pc_out(pc_out)
    );

    // Clock generation
    always #5 clk = ~clk; // Clock period of 10 units

    initial begin
        $dumpfile("pc_tb.vcd");
        $dumpvars(0, pc_tb);
        // Initialize inputs
        clk = 0;
        rst = 0;
        en = 0;
        next_pc = 0;

        // Apply reset
        rst = 1;
        #10 rst = 0;

        // Test normal operation
        en = 1;
        next_pc = 32'h00000004;
        #10;

        next_pc = 32'h00000008;
        #10;

        next_pc = 32'h0000000C;
        #10;

        // Test stall (hold PC)
        en = 0;
        #10;

        // Test reset again
        rst = 1;
        #10 rst = 0;

        // Finish the simulation
        $finish;
    end

endmodule

risc-v/program_counter/pc_tb.vcd
$date
	Thu Aug 29 10:16:11 2024
$end
$version
	Icarus Verilog
$end
$timescale
	1ps
$end
$scope module pc_tb $end
$var wire 32 ! pc_out [31:0] $end
$var reg 1 " clk $end
$var reg 1 # en $end
$var reg 32 $ next_pc [31:0] $end
$var reg 1 % rst $end
$scope module pc_uut $end
$var wire 1 " clk $end
$var wire 1 # en $end
$var wire 32 & next_pc [31:0] $end
$var wire 1 % rst $end
$var reg 32 ' pc_out [31:0] $end
$upscope $end
$upscope $end
$enddefinitions $end
$comment Show the parameter values. $end
$dumpall
$end
#0
$dumpvars
b0 '
b0 &
1%
b0 $
0#
0"
b0 !
$end
#5
1"
#10
0"
b100 $
b100 &
1#
0%
#15
b100 !
b100 '
1"
#20
0"
b1000 $
b1000 &
#25
b1000 !
b1000 '
1"
#30
0"
b1100 $
b1100 &
#35
b1100 !
b1100 '
1"
#40
0"
0#
#45
1"
#50
b0 !
b0 '
0"
1%
#55
1"
#60
0"
0%
