risc-v/risc-v-defines.v
// Register file defines
`define NUM_REGISTERS 32
`define READ_X0_ZERO 5'b00000   // zero
`define READ_X1_RA 5'b00001     // return address
`define READ_X2_SP 5'b00010     // stack pointer 
`define READ_X3_GP 5'b00011     // global pointer
`define READ_X4_TP 5'b00100     // thread pointer
`define READ_X5_T0 5'b00101     // temporary/alternate link register
`define READ_X6_T1 5'b00110     // temporary
`define READ_X7_T2 5'b00111     // temporary
`define READ_X8_S0 5'b01000     // saved register/frame pointer
`define READ_X9_S1 5'b01001     // saved register
`define READ_X10_A0 5'b01010    // function argument/return value
`define READ_X11_A1 5'b01011    // function argument/return value
`define READ_X12_A2 5'b01100    // function argument
`define READ_X13_A3 5'b01101    // function argument
`define READ_X14_A4 5'b01110    // function argument
`define READ_X15_A5 5'b01111    // function argument
`define READ_X16_A6 5'b10000    // function argument
`define READ_X17_A7 5'b10001    // function argument
`define READ_X18_S2 5'b10010    // saved register
`define READ_X19_S3 5'b10011    // saved register
`define READ_X20_S4 5'b10100    // saved register
`define READ_X21_S5 5'b10101    // saved register
`define READ_X22_S6 5'b10110    // saved register
`define READ_X23_S7 5'b10111    // saved register
`define READ_X24_S8 5'b11000    // saved register
`define READ_X25_S9 5'b11001    // saved register
`define READ_X26_S10 5'b11010   // saved register
`define READ_X27_S11 5'b11011   // saved register
`define READ_X28_T3 5'b11100    // temporary
`define READ_X29_T4 5'b11101    // temporary
`define READ_X31_T6 5'b11110    // temporary
`define READ_X30_T5 5'b11111    // temporary

risc-v/register_file/reg_file.v
`include "../risc-v-defines.v"

module reg_file #(parameter wth = 32) (
    input wire clk,       // Clock
    input wire we,        // Write enable
    input wire rst,       // Reset
    input wire [4:0] ra1, // Read address 1
    input wire [4:0] ra2, // Read address 2
    input wire [4:0] wa,  // Write address
    input wire [31:0] wd, // Write data
    output reg [31:0] rd1,// Read data 1
    output reg [31:0] rd2 // Read data 2
);

reg  [31:0] rg_x1_ra;      // return address
reg  [31:0] rg_x2_sp;      // stack pointer 
reg  [31:0] rg_x3_gp;      // global pointer
reg  [31:0] rg_x4_tp;      // thread pointer
reg  [31:0] rg_x5_t0;      // temporary/alternate link register
reg  [31:0] rg_x6_t1;      // temporary
reg  [31:0] rg_x7_t2;      // temporary
reg  [31:0] rg_x8_s0;      // saved register/frame pointer
reg  [31:0] rg_x9_s1;      // saved register
reg  [31:0] rg_x10_a0;     // function argument/return value
reg  [31:0] rg_x11_a1;     // function argument/return value
reg  [31:0] rg_x12_a2;     // function argument
reg  [31:0] rg_x13_a3;     // function argument
reg  [31:0] rg_x14_a4;     // function argument
reg  [31:0] rg_x15_a5;     // function argument
reg  [31:0] rg_x16_a6;     // function argument
reg  [31:0] rg_x17_a7;     // function argument
reg  [31:0] rg_x18_s2;     // saved register
reg  [31:0] rg_x19_s3;     // saved register
reg  [31:0] rg_x20_s4;     // saved register
reg  [31:0] rg_x21_s5;     // saved register
reg  [31:0] rg_x22_s6;     // saved register
reg  [31:0] rg_x23_s7;     // saved register
reg  [31:0] rg_x24_s8;     // saved register
reg  [31:0] rg_x25_s9;     // saved register
reg  [31:0] rg_x26_s10;    // saved register
reg  [31:0] rg_x27_s11;    // saved register
reg  [31:0] rg_x28_t3;     // temporary
reg  [31:0] rg_x29_t4;     // temporary
reg  [31:0] rg_x30_t5;     // temporary
reg  [31:0] rg_x31_t6;     // temporary
    
always @ (posedge clk) begin
    if (rst == 1'b1) begin // If reset enabled, reset all registers
        rg_x1_ra    =  32'h00000000;
        rg_x2_sp    =  32'h00000000;  
        rg_x3_gp    =  32'h00000000;  
        rg_x4_tp    =  32'h00000000;  
        rg_x5_t0    =  32'h00000000;  
        rg_x6_t1    =  32'h00000000;  
        rg_x7_t2    =  32'h00000000;  
        rg_x8_s0    =  32'h00000000;  
        rg_x9_s1    =  32'h00000000;  
        rg_x10_a0   =  32'h00000000;
        rg_x11_a1   =  32'h00000000;
        rg_x12_a2   =  32'h00000000;
        rg_x13_a3   =  32'h00000000;
        rg_x14_a4   =  32'h00000000;
        rg_x15_a5   =  32'h00000000;
        rg_x16_a6   =  32'h00000000;
        rg_x17_a7   =  32'h00000000;
        rg_x18_s2   =  32'h00000000;
        rg_x19_s3   =  32'h00000000;
        rg_x20_s4   =  32'h00000000;
        rg_x21_s5   =  32'h00000000;
        rg_x22_s6   =  32'h00000000;
        rg_x23_s7   =  32'h00000000;
        rg_x24_s8   =  32'h00000000;
        rg_x25_s9   =  32'h00000000;
        rg_x26_s10  =  32'h00000000;
        rg_x27_s11  =  32'h00000000;
        rg_x28_t3   =  32'h00000000;
        rg_x29_t4   =  32'h00000000;
        rg_x30_t5   =  32'h00000000;
        rg_x31_t6   =  32'h00000000;
    end
    else if (we == 1'b1) begin
        case (wa)
            `READ_X1_RA  : rg_x1_ra     <= wd;
            `READ_X2_SP  : rg_x2_sp     <= wd;
            `READ_X3_GP  : rg_x3_gp     <= wd;
            `READ_X4_TP  : rg_x4_tp     <= wd;
            `READ_X5_T0  : rg_x5_t0     <= wd;
            `READ_X6_T1  : rg_x6_t1     <= wd;
            `READ_X7_T2  : rg_x7_t2     <= wd;
            `READ_X8_S0  : rg_x8_s0     <= wd;
            `READ_X9_S1  : rg_x9_s1     <= wd;
            `READ_X10_A0 : rg_x10_a0    <= wd;
            `READ_X11_A1 : rg_x11_a1    <= wd;
            `READ_X12_A2 : rg_x12_a2    <= wd;
            `READ_X13_A3 : rg_x13_a3    <= wd;
            `READ_X14_A4 : rg_x14_a4    <= wd;
            `READ_X15_A5 : rg_x15_a5    <= wd;
            `READ_X16_A6 : rg_x16_a6    <= wd;
            `READ_X17_A7 : rg_x17_a7    <= wd;
            `READ_X18_S2 : rg_x18_s2    <= wd;
            `READ_X19_S3 : rg_x19_s3    <= wd;
            `READ_X20_S4 : rg_x20_s4    <= wd;
            `READ_X21_S5 : rg_x21_s5    <= wd;
            `READ_X22_S6 : rg_x22_s6    <= wd;
            `READ_X23_S7 : rg_x23_s7    <= wd;
            `READ_X24_S8 : rg_x24_s8    <= wd;
            `READ_X25_S9 : rg_x25_s9    <= wd;
            `READ_X26_S10: rg_x26_s10   <= wd;
            `READ_X27_S11: rg_x27_s11   <= wd;
            `READ_X28_T3 : rg_x28_t3    <= wd;
            `READ_X29_T4 : rg_x29_t4    <= wd;
            `READ_X31_T6 : rg_x30_t5    <= wd;
            `READ_X30_T5 : rg_x31_t6    <= wd;
        endcase
    end
end

always @ (*) begin
    case (ra1)
        `READ_X0_ZERO: rd1 <= 32'b0;
        `READ_X1_RA  : rd1 <= rg_x1_ra  ;  
        `READ_X2_SP  : rd1 <= rg_x2_sp  ;  
        `READ_X3_GP  : rd1 <= rg_x3_gp  ;  
        `READ_X4_TP  : rd1 <= rg_x4_tp  ;  
        `READ_X5_T0  : rd1 <= rg_x5_t0  ;  
        `READ_X6_T1  : rd1 <= rg_x6_t1  ;  
        `READ_X7_T2  : rd1 <= rg_x7_t2  ;  
        `READ_X8_S0  : rd1 <= rg_x8_s0  ;  
        `READ_X9_S1  : rd1 <= rg_x9_s1  ;  
        `READ_X10_A0 : rd1 <= rg_x10_a0 ;  
        `READ_X11_A1 : rd1 <= rg_x11_a1 ;  
        `READ_X12_A2 : rd1 <= rg_x12_a2 ;  
        `READ_X13_A3 : rd1 <= rg_x13_a3 ;  
        `READ_X14_A4 : rd1 <= rg_x14_a4 ;  
        `READ_X15_A5 : rd1 <= rg_x15_a5 ;  
        `READ_X16_A6 : rd1 <= rg_x16_a6 ;  
        `READ_X17_A7 : rd1 <= rg_x17_a7 ;  
        `READ_X18_S2 : rd1 <= rg_x18_s2 ;  
        `READ_X19_S3 : rd1 <= rg_x19_s3 ;  
        `READ_X20_S4 : rd1 <= rg_x20_s4 ;  
        `READ_X21_S5 : rd1 <= rg_x21_s5 ;  
        `READ_X22_S6 : rd1 <= rg_x22_s6 ;  
        `READ_X23_S7 : rd1 <= rg_x23_s7 ;  
        `READ_X24_S8 : rd1 <= rg_x24_s8 ;  
        `READ_X25_S9 : rd1 <= rg_x25_s9 ;  
        `READ_X26_S10: rd1 <= rg_x26_s10;  
        `READ_X27_S11: rd1 <= rg_x27_s11;  
        `READ_X28_T3 : rd1 <= rg_x28_t3 ;  
        `READ_X29_T4 : rd1 <= rg_x29_t4 ;  
        `READ_X31_T6 : rd1 <= rg_x30_t5 ;  
        `READ_X30_T5 : rd1 <= rg_x31_t6 ;
        default:
            rd1 <= 32'b0;
    endcase
    case (ra2)
        `READ_X0_ZERO: rd2 <= 32'b0;
        `READ_X1_RA  : rd2 <= rg_x1_ra  ;  
        `READ_X2_SP  : rd2 <= rg_x2_sp  ;  
        `READ_X3_GP  : rd2 <= rg_x3_gp  ;  
        `READ_X4_TP  : rd2 <= rg_x4_tp  ;  
        `READ_X5_T0  : rd2 <= rg_x5_t0  ;  
        `READ_X6_T1  : rd2 <= rg_x6_t1  ;  
        `READ_X7_T2  : rd2 <= rg_x7_t2  ;  
        `READ_X8_S0  : rd2 <= rg_x8_s0  ;  
        `READ_X9_S1  : rd2 <= rg_x9_s1  ;  
        `READ_X10_A0 : rd2 <= rg_x10_a0 ;  
        `READ_X11_A1 : rd2 <= rg_x11_a1 ;  
        `READ_X12_A2 : rd2 <= rg_x12_a2 ;  
        `READ_X13_A3 : rd2 <= rg_x13_a3 ;  
        `READ_X14_A4 : rd2 <= rg_x14_a4 ;  
        `READ_X15_A5 : rd2 <= rg_x15_a5 ;  
        `READ_X16_A6 : rd2 <= rg_x16_a6 ;  
        `READ_X17_A7 : rd2 <= rg_x17_a7 ;  
        `READ_X18_S2 : rd2 <= rg_x18_s2 ;  
        `READ_X19_S3 : rd2 <= rg_x19_s3 ;  
        `READ_X20_S4 : rd2 <= rg_x20_s4 ;  
        `READ_X21_S5 : rd2 <= rg_x21_s5 ;  
        `READ_X22_S6 : rd2 <= rg_x22_s6 ;  
        `READ_X23_S7 : rd2 <= rg_x23_s7 ;  
        `READ_X24_S8 : rd2 <= rg_x24_s8 ;  
        `READ_X25_S9 : rd2 <= rg_x25_s9 ;  
        `READ_X26_S10: rd2 <= rg_x26_s10;  
        `READ_X27_S11: rd2 <= rg_x27_s11;  
        `READ_X28_T3 : rd2 <= rg_x28_t3 ;  
        `READ_X29_T4 : rd2 <= rg_x29_t4 ;  
        `READ_X31_T6 : rd2 <= rg_x30_t5 ;  
        `READ_X30_T5 : rd2 <= rg_x31_t6 ;
        default:
            rd2 <= 32'b0;
    endcase
end

endmodule

risc-v/register_file/reg_file_tb.v
`timescale 1ns/1ps
`include "../risc-v-defines.v"

module reg_file_tb;

    // Inputs
    reg clk;
    reg we;
    reg rst;
    reg [4:0] ra1;
    reg [4:0] ra2;
    reg [4:0] wa;
    reg [31:0] wd;

    // Outputs
    wire [31:0] rd1;
    wire [31:0] rd2;

    // Instantiate the reg_file module
    reg_file reg_file_uut (
        .clk(clk),
        .we(we),
        .rst(rst),
        .ra1(ra1),
        .ra2(ra2),
        .wa(wa),
        .wd(wd),
        .rd1(rd1),
        .rd2(rd2)
    );

    // Clock generation
    initial begin
        clk = 0;
        forever #5 clk = ~clk;  // Toggle clock every 5 time units (10 units period)
    end

    initial begin
        $dumpfile("reg_file_tb.vcd");
        $dumpvars(0, reg_file_tb);

        // Initialize Inputs
        we = 0;
        rst = 1;
        ra1 = 0;
        ra2 = 0;
        wa = 0;
        wd = 0;

        // Apply reset
        #10 rst = 0;

        // Write to register x1 (ra)
        we = 1;
        wa = `READ_X1_RA;
        wd = 32'h12345678;
        #10;

        // Write to register x2 (sp)
        wa = `READ_X2_SP;
        wd = 32'h87654321;
        #10;

        // Disable write enable
        we = 0;

        // Read from registers x1 and x2
        ra1 = `READ_X1_RA;
        ra2 = `READ_X2_SP;
        #10;

        // Display read data
        $display("rd1 = %h, expected = %h", rd1, 32'h12345678);
        $display("rd2 = %h, expected = %h", rd2, 32'h87654321);

        // Test reset functionality
        rst = 1;
        #10;
        rst = 0;
        ra1 = `READ_X1_RA;
        ra2 = `READ_X2_SP;
        #10;

        // Display read data after reset
        $display("rd1 after reset = %h, expected = %h", rd1, 32'h00000000);
        $display("rd2 after reset = %h, expected = %h", rd2, 32'h00000000);

        // Finish simulation
        $finish;
    end
endmodule

risc-v/register_file/reg_file_tb.vcd
$date
	Tue Aug 27 18:32:28 2024
$end
$version
	Icarus Verilog
$end
$timescale
	1ps
$end
$scope module reg_file_tb $end
$var wire 32 ! rd2 [31:0] $end
$var wire 32 " rd1 [31:0] $end
$var reg 1 # clk $end
$var reg 5 $ ra1 [4:0] $end
$var reg 5 % ra2 [4:0] $end
$var reg 1 & rst $end
$var reg 5 ' wa [4:0] $end
$var reg 32 ( wd [31:0] $end
$var reg 1 ) we $end
$scope module reg_file_uut $end
$var wire 1 # clk $end
$var wire 5 * ra1 [4:0] $end
$var wire 5 + ra2 [4:0] $end
$var wire 1 & rst $end
$var wire 5 , wa [4:0] $end
$var wire 32 - wd [31:0] $end
$var wire 1 ) we $end
$var parameter 32 . wth $end
$var reg 32 / rd1 [31:0] $end
$var reg 32 0 rd2 [31:0] $end
$var reg 32 1 rg_x10_a0 [31:0] $end
$var reg 32 2 rg_x11_a1 [31:0] $end
$var reg 32 3 rg_x12_a2 [31:0] $end
$var reg 32 4 rg_x13_a3 [31:0] $end
$var reg 32 5 rg_x14_a4 [31:0] $end
$var reg 32 6 rg_x15_a5 [31:0] $end
$var reg 32 7 rg_x16_a6 [31:0] $end
$var reg 32 8 rg_x17_a7 [31:0] $end
$var reg 32 9 rg_x18_s2 [31:0] $end
$var reg 32 : rg_x19_s3 [31:0] $end
$var reg 32 ; rg_x1_ra [31:0] $end
$var reg 32 < rg_x20_s4 [31:0] $end
$var reg 32 = rg_x21_s5 [31:0] $end
$var reg 32 > rg_x22_s6 [31:0] $end
$var reg 32 ? rg_x23_s7 [31:0] $end
$var reg 32 @ rg_x24_s8 [31:0] $end
$var reg 32 A rg_x25_s9 [31:0] $end
$var reg 32 B rg_x26_s10 [31:0] $end
$var reg 32 C rg_x27_s11 [31:0] $end
$var reg 32 D rg_x28_t3 [31:0] $end
$var reg 32 E rg_x29_t4 [31:0] $end
$var reg 32 F rg_x2_sp [31:0] $end
$var reg 32 G rg_x30_t5 [31:0] $end
$var reg 32 H rg_x31_t6 [31:0] $end
$var reg 32 I rg_x3_gp [31:0] $end
$var reg 32 J rg_x4_tp [31:0] $end
$var reg 32 K rg_x5_t0 [31:0] $end
$var reg 32 L rg_x6_t1 [31:0] $end
$var reg 32 M rg_x7_t2 [31:0] $end
$var reg 32 N rg_x8_s0 [31:0] $end
$var reg 32 O rg_x9_s1 [31:0] $end
$upscope $end
$upscope $end
$enddefinitions $end
$comment Show the parameter values. $end
$dumpall
b100000 .
$end
#0
$dumpvars
bx O
bx N
bx M
bx L
bx K
bx J
bx I
bx H
bx G
bx F
bx E
bx D
bx C
bx B
bx A
bx @
bx ?
bx >
bx =
bx <
bx ;
bx :
bx 9
bx 8
bx 7
bx 6
bx 5
bx 4
bx 3
bx 2
bx 1
b0 0
b0 /
b0 -
b0 ,
b0 +
b0 *
0)
b0 (
b0 '
1&
b0 %
b0 $
0#
b0 "
b0 !
$end
#5000
b0 H
b0 G
b0 E
b0 D
b0 C
b0 B
b0 A
b0 @
b0 ?
b0 >
b0 =
b0 <
b0 :
b0 9
b0 8
b0 7
b0 6
b0 5
b0 4
b0 3
b0 2
b0 1
b0 O
b0 N
b0 M
b0 L
b0 K
b0 J
b0 I
b0 F
b0 ;
1#
#10000
0#
b10010001101000101011001111000 (
b10010001101000101011001111000 -
b1 '
b1 ,
1)
0&
#15000
b10010001101000101011001111000 ;
1#
#20000
0#
b10000111011001010100001100100001 (
b10000111011001010100001100100001 -
b10 '
b10 ,
#25000
b10000111011001010100001100100001 F
1#
#30000
b10000111011001010100001100100001 !
b10000111011001010100001100100001 0
b10010001101000101011001111000 "
b10010001101000101011001111000 /
0#
b10 %
b10 +
b1 $
b1 *
0)
#35000
1#
#40000
0#
1&
#45000
b0 !
b0 0
b0 "
b0 /
b0 F
b0 ;
1#
#50000
0#
0&
