risc-v/risc-v-defines.v
// Register file defines
`define NUM_REGISTERS 32
`define READ_X0_ZERO 5'b00000   // zero
`define READ_X1_RA 5'b00001     // return address
`define READ_X2_SP 5'b00010     // stack pointer 
`define READ_X3_GP 5'b00011     // global pointer
`define READ_X4_TP 5'b00100     // thread pointer
`define READ_X5_T0 5'b00101     // temporary/alternate link register
`define READ_X6_T1 5'b00110     // temporary
`define READ_X7_T2 5'b00111     // temporary
`define READ_X8_S0 5'b01000     // saved register/frame pointer
`define READ_X9_S1 5'b01001     // saved register
`define READ_X10_A0 5'b01010    // function argument/return value
`define READ_X11_A1 5'b01011    // function argument/return value
`define READ_X12_A2 5'b01100    // function argument
`define READ_X13_A3 5'b01101    // function argument
`define READ_X14_A4 5'b01110    // function argument
`define READ_X15_A5 5'b01111    // function argument
`define READ_X16_A6 5'b10000    // function argument
`define READ_X17_A7 5'b10001    // function argument
`define READ_X18_S2 5'b10010    // saved register
`define READ_X19_S3 5'b10011    // saved register
`define READ_X20_S4 5'b10100    // saved register
`define READ_X21_S5 5'b10101    // saved register
`define READ_X22_S6 5'b10110    // saved register
`define READ_X23_S7 5'b10111    // saved register
`define READ_X24_S8 5'b11000    // saved register
`define READ_X25_S9 5'b11001    // saved register
`define READ_X26_S10 5'b11010   // saved register
`define READ_X27_S11 5'b11011   // saved register
`define READ_X28_T3 5'b11100    // temporary
`define READ_X29_T4 5'b11101    // temporary
`define READ_X31_T6 5'b11110    // temporary
`define READ_X30_T5 5'b11111    // temporary

risc-v/new_control_unit/deco_data.v
`include "../risc-v-defines.v"

module deco_data (
    // data control
    input wire [1:0] LS,
    input wire [2:0] funct3,

    // Output
    output wire [2:0] Data_T
    
);

reg [2:0] aux_data = 0;

always @(*) begin
    case (funct3)
        3'b000:
            begin
                if (LS == 2'b10) begin
                    aux_data = 3'b010;
                end else begin
                    aux_data = 3'b101;
                end
            end
        3'b001:
            begin
                if (LS == 2'b10) begin
                    aux_data = 3'b001;
                end else begin
                    aux_data = 3'b110;
                end
            end
        3'b010:
            begin
                if (LS == 2'b10) begin
                    aux_data = 3'b000;
                end else begin
                    aux_data = 3'b100;
                end
            end
        3'b100:
            begin
                aux_data = 3'b011;
            end
        3'b101:
            begin
                aux_data = 3'b111;
            end
        default:
            begin
                aux_data = 3'b000;
            end 
    endcase
end

assign Data_T = aux_data;

endmodule

risc-v/new_control_unit/deco_jump.v
`include "../risc-v-defines.v"

module deco_jump(
    // jump control
    input wire rst,
    input wire [2:0] BJ,
    input wire EXC,
    input wire [2:0] funct3,

    // deco2
    input wire flags,

    // Output
    output wire Reg,
    output wire [1:0] jump,
    output wire Branch
);

reg aux_reg = 0;
reg aux_B = 0;
reg [1:0] aux_jump;
reg aux_branch = 0;

always @(*) begin
    if (rst == 1'b1) begin
        aux_reg = 0;
        aux_jump = 2'b00;
        aux_B = 0;
    end if (EXC == 1'b1) begin
        aux_reg = 0;
        aux_jump = 2'b11;
        aux_B = 0;
    end else begin
        case (funct3)
            3'b000:
                begin
                    if (BJ == 3'b001) begin
                        aux_B = 1;
                        aux_reg = 0;
                        aux_jump = 2'b01;
                    end else begin
                        aux_B = 0;
                        aux_reg = 1;
                        aux_jump = 2'b10;
                    end
                end
            3'b001:
                begin
                    aux_B = 1;
                    aux_reg = 0;
                    aux_jump = 2'b01;
                end
            3'b100:
                begin
                    aux_B = 1;
                    aux_reg = 0;
                    aux_jump = 2'b01;
                end
            3'b101:
                begin
                    aux_B = 1;
                    aux_reg = 0;
                    aux_jump = 2'b01;
                end
            3'b110:
                begin
                    aux_B = 1;
                    aux_reg = 0;
                    aux_jump = 2'b01;
                end
            3'b111:
                begin
                    aux_B = 1;
                    aux_reg = 0;
                    aux_jump = 2'b01;
                end
            default:
                begin
                    case (BJ)
                        3'b100:
                            begin
                                aux_B = 0;
                                aux_reg = 0;
                                aux_jump = 2'b10;
                            end
                        3'b010:
                            begin
                                aux_B = 0;
                                aux_reg = 0;
                                aux_jump = 2'b10;
                            end
                        3'b000:
                            begin
                                aux_B = 0;
                                aux_reg = 0;
                                aux_jump = 2'b01;
                            end
                        default:
                            begin
                                aux_B = 0;
                                aux_reg = 0;
                                aux_jump = 2'b00;
                            end
                    endcase
                end
        endcase
    end
end

assign Branch = aux_B;
assign Reg = aux_reg;
assign jump = aux_jump;

endmodule

risc-v/new_control_unit/deco_op.v
`include "../risc-v-defines.v"

module deco_op (
    // Deco input
    input wire RI,
    input wire [2:0] funct3,
    input wire [6:0] funct7,

    // Multiplex input
    input wire [4:0] in_shamt,
    input wire [4:0] RD2,
    // input zero = 5'b0000
    
    // Output
    output wire [3:0] alu_op,
    output wire [4:0] SHAMT
);

// Auxiliares
reg [1:0] aux_S = 0;
reg [3:0] aux_alu_op = 0;
reg [4:0] aux_SHAMT = 0;

always @(*) begin
    case (funct7)
        7'b0100000:
            begin
                case (funct3)
                    `FUNCT3_SUB:
                        begin
                            aux_alu_op = 4'b0010;
                            aux_S = 2'b00;
                        end
                    `FUNCT3_SRA:
                        begin
                            aux_alu_op = 4'b1000;
                            if (RI == 3'b001) begin
                                aux_S = 2'b10;
                            end else begin
                                aux_S = 2'b11;
                            end
                        end
                endcase
            end
        7'b0000000:
            begin
                case (funct3)
                    `FUNCT3_ADD:
                        begin
                            aux_alu_op = 4'b0001;
                            aux_S = 2'b00;
                        end
                    `FUNCT3_SLL:
                        begin
                            aux_alu_op = 4'b0110;
                            if (RI == 3'b001) begin
                                aux_S = 2'b10;
                            end else begin
                                aux_S = 2'b11;
                            end
                        end
                    `FUNCT3_XOR:
                        begin
                            aux_alu_op = 4'b0101;
                            aux_S = 2'b00;
                        end
                    `FUNCT3_SRL:
                        begin
                            aux_alu_op = 4'b0111;
                            if (RI == 3'b001) begin
                                aux_S = 2'b10;
                            end else begin
                                aux_S = 2'b11;
                            end
                        end
                    `FUNCT3_OR:
                        begin
                            aux_alu_op = 4'b0100;
                            aux_S = 2'b00;
                        end
                    `FUNCT3_AND:
                        begin
                            aux_alu_op = 4'b0011;
                            aux_S = 2'b00;
                        end
                endcase
            end
        default:
            begin
                aux_S = 2'b00;
                case (funct3)
                    3'b000:
                        begin
                            if (RI == 2'b110) begin
                                aux_alu_op = 4'b0001;
                            end else begin
                                aux_alu_op = 4'b1111;
                            end
                        end
                    3'b001:
                        begin
                            if (RI == 2'b110) begin
                                aux_alu_op = 4'b0001;
                            end else begin
                                aux_alu_op = 4'b1111;
                            end
                        end
                    3'b010:
                        begin
                            aux_alu_op = 4'b0001;
                        end
                    3'b100:
                        begin
                            if (RI == 2'b110) begin
                                aux_alu_op = 4'b0001;
                            end else begin
                                aux_alu_op = 4'b1111;
                            end
                        end
                    3'b101:
                        begin
                            if (RI == 2'b110) begin
                                aux_alu_op = 4'b0001;
                            end else begin
                                aux_alu_op = 4'b1111;
                            end
                        end
                    3'b110:
                        begin
                            aux_alu_op = 4'b0010;
                        end
                    3'b111:
                        begin
                            aux_alu_op = 4'b0010;
                        end
                    default:
                        begin
                            aux_alu_op = 4'b0000;
                        end
                endcase
            end
    endcase
    case (aux_S)
        2'b10:
            begin
                aux_SHAMT = RD2;
            end
        2'b11:
            begin
                aux_SHAMT = in_shamt;
            end
        default:
            begin
                aux_SHAMT = 5'b00000;
            end
    endcase 
end

assign SHAMT = aux_SHAMT;
assign alu_op = aux_alu_op;

endmodule

risc-v/new_control_unit/control_principal.v
`include "../risc-v-defines.v"

module control_principal (
    // Main control
    input wire clk,
    input wire rst,
    input wire [6:0] opcode,   // Opcode from the instruction

    // Internal signals
    output wire [2:0] RI,
    output wire [1:0] LS,
    output wire [2:0] BJ,
    output wire EXC,
    
    // Pass
    output wire CLK,
    output wire RST,
    
    // Output
    output wire [1:0] Data_S,
    output wire Reg_W,
    output wire ALU_S,
    output wire Mem_W,
    output wire Mem_R
    
);

// Auxiliares para operar
reg [2:0] aux_RI = 0;
reg [1:0] aux_LS = 0;
reg [2:0] aux_BJ = 0;
reg aux_EXC = 0;
reg [1:0] aux_Data_S = 0;
reg aux_Reg_W = 0;
reg aux_ALU_S = 0;
reg aux_Mem_W = 0;
reg aux_Mem_R = 0;

always @(posedge clk) begin
    case (opcode)
        `OPCODE_R:
            begin
                aux_RI = 3'b001;
                aux_LS = 2'b00;
                aux_BJ = 3'b000;
                aux_EXC = 0;
                aux_Data_S = 2'b00;
                aux_Reg_W = 1;
                aux_ALU_S = 0;
                aux_Mem_W = 0;
                aux_Mem_R = 0;
            end
        `OPCODE_I:
            begin
                aux_RI = 3'b010;
                aux_LS = 2'b00;
                aux_BJ = 3'b000;
                aux_EXC = 0;
                aux_Data_S = 2'b00;
                aux_Reg_W = 1;
                aux_ALU_S = 1;
                aux_Mem_W = 0;
                aux_Mem_R = 0;
            end
        `OPCODE_LOAD:
            begin
                aux_RI = 3'b110;
                aux_LS = 2'b10;
                aux_BJ = 3'b000;
                aux_EXC = 0;
                aux_Data_S = 2'b01;
                aux_Reg_W = 1;
                aux_ALU_S = 1;
                aux_Mem_W = 0;
                aux_Mem_R = 1;
            end
        `OPCODE_STORE:
            begin
                aux_RI = 3'b110;
                aux_LS = 2'b01;
                aux_BJ = 3'b000;
                aux_EXC = 0;
                aux_Data_S = 2'b01;
                aux_Reg_W = 0;
                aux_ALU_S = 1;
                aux_Mem_W = 1;
                aux_Mem_R = 0;
            end
        `OPCODE_BRANCH:
            begin
                aux_RI = 3'b101;
                aux_LS = 2'b00;
                aux_BJ = 3'b001;
                aux_EXC = 0;
                aux_Data_S = 2'b00;
                aux_Reg_W = 0;
                aux_ALU_S = 0;
                aux_Mem_W = 0;
                aux_Mem_R = 0;
            end
        `OPCODE_JALR:
            begin
                aux_RI = 3'b000;
                aux_LS = 2'b00;
                aux_BJ = 3'b101;
                aux_EXC = 0;
                aux_Data_S = 2'b11;
                aux_Reg_W = 1;
                aux_ALU_S = 0;
                aux_Mem_W = 0;
                aux_Mem_R = 0;
            end
        `OPCODE_JAL:
            begin
                aux_RI = 3'b000;
                aux_LS = 2'b00;
                aux_BJ = 3'b100;
                aux_EXC = 0;
                aux_Data_S = 2'b11;
                aux_Reg_W = 1;
                aux_ALU_S = 0;
                aux_Mem_W = 0;
                aux_Mem_R = 0;
            end
        `OPCODE_AUIPC:
            begin
                aux_RI = 3'b000;
                aux_LS = 2'b00;
                aux_BJ = 3'b010;
                aux_EXC = 0;
                aux_Data_S = 2'b00;
                aux_Reg_W = 0;
                aux_ALU_S = 0;
                aux_Mem_W = 0;
                aux_Mem_R = 0;
            end
        `OPCODE_LUI:
            begin
                aux_RI = 3'b000;
                aux_LS = 2'b00;
                aux_BJ = 3'b000;
                aux_EXC = 0;
                aux_Data_S = 2'b10;
                aux_Reg_W = 1;
                aux_ALU_S = 0;
                aux_Mem_W = 0;
                aux_Mem_R = 0;
            end
        default:
            begin
                aux_RI = 3'b000;
                aux_LS = 2'b00;
                aux_BJ = 3'b000;
                aux_EXC = 1;
                aux_Data_S = 2'b00;
                aux_Reg_W = 0;
                aux_ALU_S = 0;
                aux_Mem_W = 0;
                aux_Mem_R = 0;
            end
    endcase

end

assign RI = aux_RI;
assign LS = aux_LS;
assign BJ = aux_BJ;
assign EXC = aux_EXC;
assign Data_S = aux_Data_S;
assign Reg_W = aux_Reg_W;
assign ALU_S = aux_ALU_S;
assign Mem_W = aux_Mem_W;
assign Mem_R = aux_Mem_R;

endmodule

risc-v/new_control_unit/control_unit.v

module control_unit(
    /// control principal
    // Main control
    input wire clk,
    input wire rst,
    input wire [6:0] opcode,
    input wire [2:0] funct3,
    input wire [6:0] funct7,
    input wire [4:0] in_shamt,
    input wire [4:0] RD2,
    input wire flags,

    // Pass
    output wire CLK,
    output wire RESET,
    
    // Output
    output wire [1:0] Data_S,
    output wire Reg_W,
    output wire ALU_S,
    output wire Mem_W,
    output wire Mem_R,
    // Output
    output wire [3:0] alu_op,
    output wire [4:0] SHAMT,
    // Output
    output wire [2:0] Data_T,
    // Output
    output wire Reg,
    output wire [1:0] jump,
    output wire Branch

);

wire [2:0] RI;
wire [1:0] LS;
wire [2:0] BJ;
wire EXC;

// control principal
control_principal head (
    // Inputs
    .clk(clk),
    .rst(rst),
    .opcode(opcode),
    // Internal
    .RI(RI),
    .LS(LS),
    .BJ(BJ),
    .EXC(EXC),
    // Pass
    .CLK(CLK),
    .RST(RESET),
    // External
    .Data_S(Data_S),
    .Reg_W(Reg_W),
    .ALU_S(ALU_S),
    .Mem_W(Mem_W),
    .Mem_R(Mem_R)
);

// decodificador de alu
deco_op alu_deco(
    // Inputs
    .RI(RI),
    .funct3(funct3),
    .funct7(funct7),
    .in_shamt(in_shamt),
    .RD2(RD2),
    // Outputs
    .alu_op(alu_op),
    .SHAMT(SHAMT)
);

// decodificador de salto
deco_jump jump_deco(
    // Inputs
    .rst(rst),
    .BJ(BJ),
    .EXC(EXC),
    .funct3(funct3),
    .flags(flags),
    // Outputs
    .Reg(Reg),
    .jump(jump),
    .Branch(Branch)
);

// decodificador de data
deco_data data_deco(
    // Inputs
    .LS(LS),
    .funct3(funct3),
    // Outputs
    .Data_T(Data_T)
);

endmodule

risc-v/new_control_unit/control_unit_tb.v
`timescale 1ns / 1ps

module control_unit_tb;

    // Inputs
    reg clk;
    reg rst;
    reg [6:0] opcode;
    reg [2:0] funct3;
    reg [6:0] funct7;
    reg [4:0] in_shamt;
    reg [4:0] RD2;
    reg flags;

    // Outputs
    wire [1:0] Data_S;
    wire Reg_W;
    wire ALU_S;
    wire Mem_W;
    wire Mem_R;
    wire [3:0] alu_op;
    wire [4:0] SHAMT;
    wire [2:0] Data_T;
    wire Reg;
    wire [1:0] jump;
    wire Branch;

    // Instantiate the control_unit
    control_unit uut (
        .clk(clk),
        .rst(rst),
        .opcode(opcode),
        .funct3(funct3),
        .funct7(funct7),
        .in_shamt(in_shamt),
        .RD2(RD2),
        .flags(flags),
        .Data_S(Data_S),
        .Reg_W(Reg_W),
        .ALU_S(ALU_S),
        .Mem_W(Mem_W),
        .Mem_R(Mem_R),
        .alu_op(alu_op),
        .SHAMT(SHAMT),
        .Data_T(Data_T),
        .Reg(Reg),
        .jump(jump),
        .Branch(Branch)
    );

    // Clock generation
    always begin
        #5 clk = ~clk;  // 100 MHz clock
    end

    // Stimulus block
    initial begin
        $dumpfile("control_unit_tb.vcd");
        $dumpvars(0, control_unit_tb);
        // Initialize inputs
        clk = 0;
        rst = 0;
        opcode = 7'b0;
        funct3 = 3'b0;
        funct7 = 7'b0;
        in_shamt = 5'b0;
        RD2 = 5'b0;
        flags = 0;

        // Apply reset
        rst = 0;
        #10;
        rst = 0;

        // Test case 1: R-type instruction
        opcode = 7'b0110011;  // R-type opcode (ADD, SUB, etc.)
        funct3 = 3'b000;      // ADD
        funct7 = 7'b0000000;  // Normal funct7 for ADD
        in_shamt = 5'b0;
        RD2 = 5'b0;
        flags = 0;
        #10;

        // Test case 2: I-type instruction (e.g., ADDI)
        opcode = 7'b0010011;  // I-type opcode (ADDI, etc.)
        funct3 = 3'b000;      // ADDI
        funct7 = 7'b0000000;  // No funct7 for I-type
        in_shamt = 5'b0;
        RD2 = 5'b0;
        flags = 0;
        #10;

        // Test case 3: Branch instruction (BEQ)
        opcode = 7'b1100011;  // Branch opcode (BEQ, etc.)
        funct3 = 3'b000;      // BEQ
        funct7 = 7'b0000000;  // No funct7 for BEQ
        in_shamt = 5'b0;
        RD2 = 5'b0;
        flags = 1;            // Condition met for branch
        #10;

        // Test case 4: Load instruction (LW)
        opcode = 7'b0000011;  // Load opcode (LW, etc.)
        funct3 = 3'b010;      // LW
        funct7 = 7'b0000000;  // No funct7 for LW
        in_shamt = 5'b0;
        RD2 = 5'b0;
        flags = 0;
        #10;

        // Test case 5: Store instruction (SW)
        opcode = 7'b0100011;  // Store opcode (SW, etc.)
        funct3 = 3'b010;      // SW
        funct7 = 7'b0000000;  // No funct7 for SW
        in_shamt = 5'b0;
        RD2 = 5'b0;
        flags = 0;
        #10;

        // Test case 6: Jump instruction (JAL)
        opcode = 7'b1101111;  // Jump opcode (JAL, etc.)
        funct3 = 3'b000;      // JAL
        funct7 = 7'b0000000;  // No funct7 for JAL
        in_shamt = 5'b0;
        RD2 = 5'b0;
        flags = 0;
        #10;

        // Test case 7: Load upper immediate (LUI)
        opcode = 7'b0110111;  // LUI opcode
        funct3 = 3'b000;      // LUI
        funct7 = 7'b0000000;  // No funct7 for LUI
        in_shamt = 5'b0;
        RD2 = 5'b0;
        flags = 0;
        #10;

        // Test case 8: AUIPC (Add Upper Immediate to PC)
        opcode = 7'b0010111;  // AUIPC opcode
        funct3 = 3'b000;      // AUIPC
        funct7 = 7'b0000000;  // No funct7 for AUIPC
        in_shamt = 5'b0;
        RD2 = 5'b0;
        flags = 0;
        #10;

        // Finish the simulation
        $finish;
    end

    // Monitor the outputs
    initial begin
        $monitor("Time = %0d, Opcode = %b, Data_S = %b, Reg_W = %b, ALU_S = %b, Mem_W = %b, Mem_R = %b, alu_op = %b, SHAMT = %b, Data_T = %b, Reg = %b, jump = %b, Branch = %b",
                 $time, opcode, Data_S, Reg_W, ALU_S, Mem_W, Mem_R, alu_op, SHAMT, Data_T, Reg, jump, Branch);
    end

endmodule

risc-v/new_control_unit/control_unit_tb.vcd
$date
	Mon Nov 18 17:54:44 2024
$end
$version
	Icarus Verilog
$end
$timescale
	1ps
$end
$scope module control_unit_tb $end
$var wire 2 ! jump [1:0] $end
$var wire 4 " alu_op [3:0] $end
$var wire 5 # SHAMT [4:0] $end
$var wire 1 $ Reg_W $end
$var wire 1 % Reg $end
$var wire 1 & Mem_W $end
$var wire 1 ' Mem_R $end
$var wire 3 ( Data_T [2:0] $end
$var wire 2 ) Data_S [1:0] $end
$var wire 1 * Branch $end
$var wire 1 + ALU_S $end
$var reg 5 , RD2 [4:0] $end
$var reg 1 - clk $end
$var reg 1 . flags $end
$var reg 3 / funct3 [2:0] $end
$var reg 7 0 funct7 [6:0] $end
$var reg 5 1 in_shamt [4:0] $end
$var reg 7 2 opcode [6:0] $end
$var reg 1 3 rst $end
$scope module uut $end
$var wire 1 4 CLK $end
$var wire 5 5 RD2 [4:0] $end
$var wire 1 6 RESET $end
$var wire 1 - clk $end
$var wire 1 . flags $end
$var wire 3 7 funct3 [2:0] $end
$var wire 7 8 funct7 [6:0] $end
$var wire 5 9 in_shamt [4:0] $end
$var wire 7 : opcode [6:0] $end
$var wire 1 3 rst $end
$var wire 2 ; jump [1:0] $end
$var wire 4 < alu_op [3:0] $end
$var wire 5 = SHAMT [4:0] $end
$var wire 1 $ Reg_W $end
$var wire 1 % Reg $end
$var wire 3 > RI [2:0] $end
$var wire 1 & Mem_W $end
$var wire 1 ' Mem_R $end
$var wire 2 ? LS [1:0] $end
$var wire 1 @ EXC $end
$var wire 3 A Data_T [2:0] $end
$var wire 2 B Data_S [1:0] $end
$var wire 1 * Branch $end
$var wire 3 C BJ [2:0] $end
$var wire 1 + ALU_S $end
$scope module alu_deco $end
$var wire 5 D RD2 [4:0] $end
$var wire 1 E RI $end
$var wire 5 F SHAMT [4:0] $end
$var wire 4 G alu_op [3:0] $end
$var wire 3 H funct3 [2:0] $end
$var wire 7 I funct7 [6:0] $end
$var wire 5 J in_shamt [4:0] $end
$var reg 2 K aux_S [1:0] $end
$var reg 5 L aux_SHAMT [4:0] $end
$var reg 4 M aux_alu_op [3:0] $end
$upscope $end
$scope module data_deco $end
$var wire 3 N Data_T [2:0] $end
$var wire 3 O funct3 [2:0] $end
$var wire 2 P LS [1:0] $end
$var reg 3 Q aux_data [2:0] $end
$upscope $end
$scope module head $end
$var wire 1 + ALU_S $end
$var wire 3 R BJ [2:0] $end
$var wire 1 4 CLK $end
$var wire 2 S Data_S [1:0] $end
$var wire 1 @ EXC $end
$var wire 2 T LS [1:0] $end
$var wire 1 ' Mem_R $end
$var wire 1 & Mem_W $end
$var wire 1 6 RST $end
$var wire 1 $ Reg_W $end
$var wire 1 - clk $end
$var wire 7 U opcode [6:0] $end
$var wire 1 3 rst $end
$var wire 3 V RI [2:0] $end
$var reg 1 W aux_ALU_S $end
$var reg 3 X aux_BJ [2:0] $end
$var reg 2 Y aux_Data_S [1:0] $end
$var reg 1 Z aux_EXC $end
$var reg 2 [ aux_LS [1:0] $end
$var reg 1 \ aux_Mem_R $end
$var reg 1 ] aux_Mem_W $end
$var reg 3 ^ aux_RI [2:0] $end
$var reg 1 _ aux_Reg_W $end
$upscope $end
$scope module jump_deco $end
$var wire 3 ` BJ [2:0] $end
$var wire 1 * Branch $end
$var wire 1 @ EXC $end
$var wire 1 % Reg $end
$var wire 1 . flags $end
$var wire 3 a funct3 [2:0] $end
$var wire 2 b jump [1:0] $end
$var wire 1 3 rst $end
$var reg 1 c aux_B $end
$var reg 1 d aux_branch $end
$var reg 2 e aux_jump [1:0] $end
$var reg 1 f aux_reg $end
$upscope $end
$upscope $end
$upscope $end
$enddefinitions $end
$comment Show the parameter values. $end
$dumpall
$end
#0
$dumpvars
1f
b10 e
0d
0c
b10 b
b0 a
b0 `
0_
b0 ^
0]
0\
b0 [
0Z
b0 Y
b0 X
0W
b0 V
b0 U
b0 T
b0 S
b0 R
b101 Q
b0 P
b0 O
b101 N
b1 M
b0 L
b0 K
b0 J
b0 I
b0 H
b1 G
b0 F
0E
b0 D
b0 C
b0 B
b101 A
0@
b0 ?
b0 >
b0 =
b1 <
b10 ;
b0 :
b0 9
b0 8
b0 7
z6
b0 5
z4
03
b0 2
b0 1
b0 0
b0 /
0.
0-
b0 ,
0+
0*
b0 )
b101 (
0'
0&
1%
0$
b0 #
b1 "
b10 !
$end
#5000
b11 !
b11 ;
b11 b
b11 e
0%
0f
1@
1Z
1-
#10000
0-
b110011 2
b110011 :
b110011 U
#15000
b10 !
b10 ;
b10 b
b10 e
1%
1f
1E
1$
1_
0@
0Z
b1 >
b1 V
b1 ^
1-
#20000
0-
b10011 2
b10011 :
b10011 U
#25000
0E
1+
1W
b10 >
b10 V
b10 ^
1-
#30000
0-
1.
b1100011 2
b1100011 :
b1100011 U
#35000
b1 !
b1 ;
b1 b
b1 e
0%
0f
1*
1c
1E
0+
0W
0$
0_
b1 C
b1 R
b1 `
b1 X
b101 >
b101 V
b101 ^
1-
#40000
b100 (
b100 A
b100 N
b100 Q
b0 !
b0 ;
b0 b
b0 e
0*
0c
0-
0.
b10 /
b10 7
b10 H
b10 O
b10 a
b11 2
b11 :
b11 U
#45000
b1 !
b1 ;
b1 b
b1 e
b0 (
b0 A
b0 N
b0 Q
0E
1'
1\
1+
1W
1$
1_
b1 )
b1 B
b1 S
b1 Y
b0 C
b0 R
b0 `
b0 X
b10 ?
b10 P
b10 T
b10 [
b110 >
b110 V
b110 ^
1-
#50000
0-
b100011 2
b100011 :
b100011 U
#55000
b100 (
b100 A
b100 N
b100 Q
0'
0\
1&
1]
0$
0_
b1 ?
b1 P
b1 T
b1 [
1-
#60000
b101 (
b101 A
b101 N
b101 Q
b10 !
b10 ;
b10 b
b10 e
1%
1f
0-
b0 /
b0 7
b0 H
b0 O
b0 a
b1101111 2
b1101111 :
b1101111 U
#65000
0&
0]
0+
0W
1$
1_
b11 )
b11 B
b11 S
b11 Y
b100 C
b100 R
b100 `
b100 X
b0 ?
b0 P
b0 T
b0 [
b0 >
b0 V
b0 ^
1-
#70000
0-
b110111 2
b110111 :
b110111 U
#75000
b10 )
b10 B
b10 S
b10 Y
b0 C
b0 R
b0 `
b0 X
1-
#80000
0-
b10111 2
b10111 :
b10111 U
#85000
0$
0_
b0 )
b0 B
b0 S
b0 Y
b10 C
b10 R
b10 `
b10 X
1-
